[{"item_id":14030002,"mask":"HairBottom"},{"item_id":14120002,"mask":"HairBottom"},{"item_id":14100002,"mask":"HairBottom"},{"item_id":14110002,"mask":"HairBottom"},{"item_id":14130002,"mask":"HairBottom"},{"item_id":14020002,"mask":"HairBottom"},{"item_id":14080002,"mask":"HairBottom"},{"item_id":14070002,"mask":"HairBottom"},{"item_id":14040002,"mask":"HairBottom"},{"item_id":14050002,"mask":"HairBottom"},{"item_id":14060002,"mask":"HairBottom"},{"item_id":14090002,"mask":"HairBottom"},{"item_id":12030002,"mask":"HairFront"},{"item_id":12120002,"mask":"HairFull"},{"item_id":12100002,"mask":"HairBottom"},{"item_id":12110002,"mask":"HairBottom"},{"item_id":12130002,"mask":"HairFull"},{"item_id":12020002,"mask":"HairBottom"},{"item_id":12080002,"mask":"HairBottom"},{"item_id":12070002,"mask":"HairBottom"},{"item_id":12040002,"mask":"HairBottom"},{"item_id":12050002,"mask":"HairFull"},{"item_id":12140002,"mask":"HairBottom"},{"item_id":12060002,"mask":"HairFront"},{"item_id":12090002,"mask":"HairBottom"},{"item_id":10030002,"mask":"HairFront"},{"item_id":10120002,"mask":"HairBottom"},{"item_id":10100002,"mask":"HairBottom"},{"item_id":10110002,"mask":"HairFull"},{"item_id":10130002,"mask":"HairFront"},{"item_id":10020002,"mask":"HairFront"},{"item_id":10080002,"mask":"HairFront"},{"item_id":10070002,"mask":"HairBottom"},{"item_id":10040002,"mask":"HairBottom"},{"item_id":10050002,"mask":"HairFull"},{"item_id":10140002,"mask":"HairBottom"},{"item_id":10060002,"mask":"HairFront"},{"item_id":10090002,"mask":"HairBottom"},{"item_id":1150008,"mask":"HairBottom"},{"item_id":1715770651,"mask":"HairFull"},{"item_id":143662070,"mask":"HairFull"},{"item_id":1880113899,"mask":"HairBottom"},{"item_id":1150012,"mask":"HairBottom"},{"item_id":1951915597,"mask":"HairFull"},{"item_id":928694408,"mask":"HairFull"},{"item_id":273992794,"mask":"HairBottom"},{"item_id":1150016,"mask":"HairBottom"},{"item_id":1150018,"mask":"HairBottom"},{"item_id":1150017,"mask":"HairBottom"},{"item_id":237918607,"mask":"HairFront"},{"item_id":1150004,"mask":"HairBottom"},{"item_id":114803167,"mask":"HairFull"},{"item_id":1474389962,"mask":"HairFull"},{"item_id":693942070,"mask":"HairBottom"},{"item_id":1608041758,"mask":"HairFront"},{"item_id":297902644,"mask":"HairFront"},{"item_id":411049737,"mask":"HairFront"},{"item_id":2106845290,"mask":"HairFront"},{"item_id":1150010,"mask":"HairFront"},{"item_id":1150007,"mask":"HairBottom"},{"item_id":1059702923,"mask":"HairBottom"},{"item_id":694339120,"mask":"HairFront"},{"item_id":32637744,"mask":"HairFront"},{"item_id":152294380,"mask":"HairFront"},{"item_id":922693453,"mask":"HairFront"},{"item_id":710248451,"mask":"HairFront"},{"item_id":1150001,"mask":"HairFront"},{"item_id":2075141544,"mask":"HairBottom"},{"item_id":1019751065,"mask":"HairBottom"},{"item_id":1034054663,"mask":"HairBottom"},{"item_id":1947560492,"mask":"HairBottom"},{"item_id":1661296503,"mask":"HairBottom"},{"item_id":1150005,"mask":"HairBottom"},{"item_id":1150003,"mask":"HairFront"},{"item_id":1754004451,"mask":"HairFront"},{"item_id":1160000,"mask":"HairBottom"},{"item_id":1150002,"mask":"HairFront"},{"item_id":2011139955,"mask":"HairBottom"},{"item_id":1719205000,"mask":"HairFront"},{"item_id":1150015,"mask":"None"},{"item_id":1150014,"mask":"None"},{"item_id":1150013,"mask":"None"},{"item_id":1150011,"mask":"HairBottom"},{"item_id":793048261,"mask":"HairFull"},{"item_id":1517215335,"mask":"HairBottom"},{"item_id":645068925,"mask":"HairFront"},{"item_id":2061951199,"mask":"HairFront"},{"item_id":1025624401,"mask":"HairFront"},{"item_id":1075596142,"mask":"HairFront"},{"item_id":1150009,"mask":"HairFront"}]